chexutil.cpython-36m-darwin.so
chexutil-0.0.4.dist-info/DESCRIPTION.rst
chexutil-0.0.4.dist-info/METADATA
chexutil-0.0.4.dist-info/RECORD
chexutil-0.0.4.dist-info/WHEEL
chexutil-0.0.4.dist-info/metadata.json
chexutil-0.0.4.dist-info/top_level.txt
