Metadata-Version: 2.0
Name: chexutil
Version: 0.0.4
Summary: C++ accelerated classes and functions to deal with hexagonal grids.
Home-page: https://github.com/stephanh42/chexutil
Author: Stephan Houben
Author-email: stephanh42@gmail.com
License: UNKNOWN
Platform: UNKNOWN
Requires-Dist: pybind11 (>=2.2)
